ghostscraper/__init__.py
ghostscraper/ghost_scraper.py
ghostscraper/playwright_installer.py
ghostscraper/playwright_scraper.py
ghostscraper-0.0.3.dist-info/METADATA
ghostscraper-0.0.3.dist-info/WHEEL
ghostscraper-0.0.3.dist-info/top_level.txt
ghostscraper-0.0.3.dist-info/RECORD
