Metadata-Version: 2.4
Name: ghostscraper
Version: 0.0.3
Summary: A Playwright-based web scraper with caching capabilities
Author-email: Arved Klöhn <arved.kloehn@gmail.com>
License: MIT
Project-URL: Homepage, https://github.com/Redundando/ghostscraper
Project-URL: Bug Tracker, https://github.com/Redundando/ghostscraper/issues
Classifier: Programming Language :: Python :: 3
Classifier: License :: OSI Approved :: MIT License
Classifier: Operating System :: OS Independent
Requires-Python: >=3.7
Requires-Dist: beautifulsoup4
Requires-Dist: cacherator
Requires-Dist: html2text
Requires-Dist: logorator
Requires-Dist: newspaper4k
Requires-Dist: playwright
Requires-Dist: python-slugify
Requires-Dist: lxml_html_clean
